azure/__init__.py
azure/gen1/__init__.py
azure/gen1/gen1.py
azure/gen1/helper.py
azure/gen2/__init__.py
azure/gen2/gen2.py
azure/gen2/helper.py
azure_storage_helper-0.3.3.dist-info/METADATA
azure_storage_helper-0.3.3.dist-info/WHEEL
azure_storage_helper-0.3.3.dist-info/licenses/LICENSE.txt
azure_storage_helper-0.3.3.dist-info/RECORD
