Metadata-Version: 2.4
Name: azure-storage-helper
Version: 0.3.3
Summary: Azure Storage Helper
Author-email: gbhwang <hwanggb1229@gmail.com>
License-File: LICENSE.txt
Requires-Python: >=3.8
Requires-Dist: azure-identity>=1.21.0
Requires-Dist: azure-storage-blob>=12.25.1
Requires-Dist: azure-storage-file-datalake>=12.20.0
Requires-Dist: joblib>=1.4.2
Requires-Dist: pandas>=2.0.3
Requires-Dist: pyarrow>=17.0.0
Requires-Dist: pyyaml>=6.0.2
